neurocode/__init__.py
neurocode/datasets/__init__.py
neurocode/datasets/recording.py
neurocode/datasets/simulated.py
neurocode/datasets/utils.py
neurocode/datautil/__init__.py
neurocode/datautil/transforms.py
neurocode/datautil/visualization.py
neurocode/models/__init__.py
neurocode/models/blanco.py
neurocode/models/contrastive.py
neurocode/models/cpc.py
neurocode/models/resnet.py
neurocode/models/simclr.py
neurocode/models/stagernet.py
neurocode/models/utils.py
neurocode/samplers/__init__.py
neurocode/samplers/base.py
neurocode/samplers/contrastive_view.py
neurocode/samplers/recording_relative_positioning.py
neurocode/samplers/recording_simclr.py
neurocode/samplers/relative_positioning.py
neurocode/samplers/scalogram_simclr.py
neurocode/samplers/signal_simclr.py
neurocode/samplers/temporal_shuffling.py
neurocode/training/__init__.py
neurocode/training/simclr.py
neurocode-1.0.0.dist-info/LICENSE
neurocode-1.0.0.dist-info/METADATA
neurocode-1.0.0.dist-info/WHEEL
neurocode-1.0.0.dist-info/RECORD
