Metadata-Version: 2.1
Name: neurocode
Version: 1.0.0
Summary: 🧠 EEG/MEG self-supervised learning toolbox.
Home-page: https://github.com/neurocode-ai/neurocode
License: MIT
Keywords: deep-learning,meg,eeg,self-supervised-learning,simclr
Author: Wilhelm Ågren
Author-email: wilhelmagren98@gmail.com
Requires-Python: >=3.9,<3.13
Classifier: Intended Audience :: Developers
Classifier: License :: OSI Approved :: MIT License
Classifier: Operating System :: OS Independent
Classifier: Programming Language :: Python :: 3
Classifier: Programming Language :: Python :: 3.9
Classifier: Programming Language :: Python :: 3.10
Classifier: Programming Language :: Python :: 3.11
Classifier: Programming Language :: Python :: 3.12
Classifier: Programming Language :: Python :: 3.8
Requires-Dist: matplotlib (>=3.8.2,<4.0.0)
Requires-Dist: mne (>=1.5.1,<2.0.0)
Requires-Dist: numpy (>=1.26.2,<2.0.0)
Requires-Dist: pandas (>=2.1.3,<3.0.0)
Requires-Dist: pillow (>=10.1.0,<11.0.0)
Requires-Dist: scikit-learn (>=1.3.2,<2.0.0)
Requires-Dist: torch (==2.1.1+cpu)
Requires-Dist: torchvision (==0.16.1+cpu)
Requires-Dist: tqdm (>=4.66.1,<5.0.0)
Requires-Dist: umap-learn (>=0.5.0,<0.6.0)
Project-URL: Bug tracker, https://github.com/neurocode-ai/neurocode/issues
Project-URL: Repository, https://github.com/neurocode-ai/neurocode
